lightly_utils/__init__.py
lightly_utils/image_processing/__init__.py
lightly_utils/image_processing/_data.py
lightly_utils/image_processing/exifdata.py
lightly_utils/image_processing/metadata.py
lightly_utils/image_processing/thumbnail.py
lightly_utils-0.0.2.dist-info/METADATA
lightly_utils-0.0.2.dist-info/WHEEL
lightly_utils-0.0.2.dist-info/top_level.txt
lightly_utils-0.0.2.dist-info/RECORD
