Metadata-Version: 2.1
Name: lightly-utils
Version: 0.0.2
Summary: A utility package for lightly
Home-page: UNKNOWN
Author: Lightly
Author-email: philipp@lightly.ai
License: MIT
Project-URL: Homepage, https://www.lightly.ai
Project-URL: Web-App, https://app.lightly.ai
Project-URL: Documentation, https://docs.lightly.ai
Project-URL: Github, https://github.com/lightly-ai/lightly
Project-URL: Discord, https://discord.gg/xvNJW94
Platform: UNKNOWN
Classifier: Development Status :: 5 - Production/Stable
Classifier: Intended Audience :: Developers
Classifier: Intended Audience :: Education
Classifier: Intended Audience :: Science/Research
Classifier: Topic :: Scientific/Engineering
Classifier: Topic :: Scientific/Engineering :: Mathematics
Classifier: Topic :: Scientific/Engineering :: Artificial Intelligence
Classifier: Topic :: Software Development
Classifier: Topic :: Software Development :: Libraries
Classifier: Topic :: Software Development :: Libraries :: Python Modules
Classifier: Programming Language :: Python :: 3
Classifier: Programming Language :: Python :: 3.6
Classifier: Programming Language :: Python :: 3.7
Classifier: Programming Language :: Python :: 3.8
Classifier: Programming Language :: Python :: 3.9
Classifier: License :: OSI Approved :: MIT License
Requires-Python: >=3.6
Requires-Dist: numpy
Requires-Dist: Pillow
